plastron/__init__.py
plastron/inode.py
plastron/mnode.py
plastron/plastron.py
plastron/screen.py
plastron-1.0.5.dist-info/LICENSE
plastron-1.0.5.dist-info/METADATA
plastron-1.0.5.dist-info/WHEEL
plastron-1.0.5.dist-info/top_level.txt
plastron-1.0.5.dist-info/RECORD
