Metadata-Version: 2.1
Name: plastron
Version: 1.0.5
Summary: An interactive shell library
Home-page: https://github.com/kavunnuggihalli/Plastron
Author: Kavun Nuggihalli
Author-email: kavunnuggihalli@gmail.com
License: UNKNOWN
Project-URL: Webpage, https://kavunnuggihalli.com/plastron/
Project-URL: Source, https://github.com/kavunnuggihalli/Plastron
Keywords: python3 interactive shell library
Platform: UNKNOWN
Classifier: Programming Language :: Python :: 3.0
Classifier: Topic :: Utilities
Classifier: Development Status :: 5 - Production/Stable
Classifier: Programming Language :: Python :: 3.7
Classifier: Topic :: System :: Shells
Classifier: Topic :: System :: System Shells
Requires-Python: >=3.0
Requires-Dist: setuptools
Requires-Dist: art
